interactions/ext/persistence/__init__.py
interactions/ext/persistence/base.py
interactions/ext/persistence/cipher.py
interactions/ext/persistence/client.py
interactions/ext/persistence/context.py
interactions/ext/persistence/extension.py
interactions/ext/persistence/parse.py
interactions/ext/persistence/persistence.py
interactions/ext/persistence/scripts.py
interactions_persistence-2.2.3.dist-info/LICENSE
interactions_persistence-2.2.3.dist-info/METADATA
interactions_persistence-2.2.3.dist-info/WHEEL
interactions_persistence-2.2.3.dist-info/entry_points.txt
interactions_persistence-2.2.3.dist-info/top_level.txt
interactions_persistence-2.2.3.dist-info/RECORD
