Metadata-Version: 2.1
Name: interactions-persistence
Version: 2.2.3
Summary: Encode json in custom_ids.
Home-page: https://github.com/interactions-py/persistence
Author: Dworv
Author-email: dwarvyt@gmail.com
License: GNU
Classifier: Programming Language :: Python :: 3
Classifier: Development Status :: 5 - Production/Stable
Classifier: License :: OSI Approved :: GNU General Public License v3 (GPLv3)
Classifier: Operating System :: OS Independent
License-File: LICENSE
Requires-Dist: discord-py-interactions
Requires-Dist: ff3
